Workbook

Sheet Anticipados
A1: Partida | B1: Tipo | C1: Monto | D1: Meses que cubre | E1: Meses consumidos | F1: Por mes | G1: Devengado | H1: Saldo al cierre
A2: Hostal · seguro (01-08 al 31-12) | B2: gasto pagado por anticipado | C2: 1236000 | D2: 12 | E2: 5 | F2: =C2/D2 | G2: =F2*E2 | H2: =C2-G2
A3: Hostal · estacionamiento (01-11 al 31-12) | B3: gasto pagado por anticipado | C3: 930000 | D3: 6 | E3: 2 | F3: =C3/D3 | G3: =F3*E3 | H3: =C3-G3
A4: Hostal · local arrendado (01-09 al 31-12) | B4: ingreso recibido por anticipado | C4: 2580000 | D4: 6 | E4: 4 | F4: =C4/D4 | G4: =F4*E4 | H4: =C4-G4
A5: Estampa Sur · arriendo de marzo | B5: gasto pagado por anticipado | C5: 580000 | D5: 1 | E5: 1 | F5: =C5/D5 | G5: =F5*E5 | H5: =C5-G5
A6: Estampa Sur · seguro anual | B6: gasto pagado por anticipado | C6: 948000 | D6: 12 | E6: 1 | F6: =C6/D6 | G6: =F6*E6 | H6: =C6-G6

Sheet Incobrables
A1: Clientes al 31-12 | B1: 6420000
A2: Porcentaje estimado incobrable | B2: 0.03
A3: Estimación requerida | B3: =B1*B2
A4: Saldo previo de la estimación | B4: 45000
A5: Ajuste del cierre | B5: =B3-B4
A6: Clientes, valor neto | B6: =B1-B3

Sheet Diario
A1: Asiento | B1: Fecha | C1: Cuenta | D1: Debe | E1: Haber | F1: Glosa
A2: A1 | B2: 31-12-2026 | C2: Gasto por seguro | D2: =Anticipados!G2 | F2: 5 meses de seguro
A3: A1 | B3: 31-12-2026 | C3: Seguro pagado por anticipado | E3: =Anticipados!G2
A4: A2 | B4: 31-12-2026 | C4: Gasto por arriendo | D4: =Anticipados!G3 | F4: 2 meses de estacionamiento
A5: A2 | B5: 31-12-2026 | C5: Arriendo pagado por anticipado | E5: =Anticipados!G3
A6: A3 | B6: 31-12-2026 | C6: Arriendo recibido por anticipado | D6: =Anticipados!G4 | F6: 4 meses del local
A7: A3 | B7: 31-12-2026 | C7: Arriendo ganado | E7: =Anticipados!G4
A8: A4 | B8: 31-12-2026 | C8: Gasto en sueldos | D8: 3150000 | F8: sueldos de diciembre, se pagan el 05-01
A9: A4 | B9: 31-12-2026 | C9: Sueldos por pagar | E9: =D8
A10: A5 | B10: 31-12-2026 | C10: Gasto en electricidad | D10: 184000 | F10: luz de diciembre, vence el 15-01
A11: A5 | B11: 31-12-2026 | C11: IVA crédito fiscal | D11: =D10*0.19
A12: A5 | B12: 31-12-2026 | C12: Cuentas por pagar | E12: =D10+D11
A13: A6 | B13: 31-12-2026 | C13: Intereses por cobrar | D13: =5000000*0.004*2 | F13: 2 meses del depósito a plazo
A14: A6 | B14: 31-12-2026 | C14: Intereses ganados | E14: =D13
A15: A7 | B15: 31-12-2026 | C15: Gasto por incobrables | D15: =Incobrables!B5 | F15: estimación al 3 % de clientes
A16: A7 | B16: 31-12-2026 | C16: Estimación de deudores incobrables | E16: =Incobrables!B5
C17: Totales | D17: =SUM(D2:D16) | E17: =SUM(E2:E16) | F17: deben ser iguales
C18: Diferencia (debe dar 0) | D18: =D17-E17
